safeu/Experiments.py
safeu/__init__.py
safeu/base.py
safeu/classification/CoTraining.py
safeu/classification/LPA.py
safeu/classification/TSVM.py
safeu/classification/__init__.py
safeu/data_quality/LEAD.py
safeu/data_quality/README.md
safeu/data_quality/SLP.py
safeu/data_quality/__init__.py
safeu/data_quality/setup.py
safeu/data_quality/slp_tools.c
safeu/data_quality/__pycache__/LEAD.cpython-37.pyc
safeu/data_quality/__pycache__/SLP.cpython-37.pyc
safeu/data_quality/__pycache__/__init__.cpython-37.pyc
safeu/data_quality/utils/ConstructGraph.py
safeu/data_quality/utils/GetConnectedComponent.py
safeu/data_quality/utils/Harmonic.py
safeu/datasets/__init__.py
safeu/datasets/base.py
safeu/datasets/covtype.py
safeu/datasets/data_manipulate.py
safeu/datasets/usps.py
"safeu/datasets/data/australian,splits,labeled=10.mat"
safeu/datasets/data/australian.mat
"safeu/datasets/data/clean1,splits,labeled=10.mat"
safeu/datasets/data/clean1.mat
safeu/datasets/data/digits.csv.gz
"safeu/datasets/data/house,splits,labeled=10.mat"
safeu/datasets/data/house.mat
"safeu/datasets/data/isolet,splits,labeled=10.mat"
safeu/datasets/data/isolet.mat
safeu/datasets/data/australian/australian_feature.csv
safeu/datasets/data/australian/australian_label.csv
safeu/datasets/data/boston/boston_house_prices_feature.csv
safeu/datasets/data/boston/boston_house_prices_label.csv
safeu/datasets/data/breast_cancer/breast_cancer_feature.csv
safeu/datasets/data/breast_cancer/breast_cancer_label.csv
safeu/datasets/data/bupa/bupa_feature.csv
safeu/datasets/data/bupa/bupa_label.csv
safeu/datasets/data/clean1/clean1_feature.csv
safeu/datasets/data/clean1/clean1_label.csv
safeu/datasets/data/diabetes/diabetes_feature.csv.gz
safeu/datasets/data/diabetes/diabetes_label.csv.gz
safeu/datasets/data/haberman/haberman_feature.csv
safeu/datasets/data/haberman/haberman_label.csv
safeu/datasets/data/house/house_feature.csv
safeu/datasets/data/house/house_label.csv
safeu/datasets/data/ionosphere/ionosphere_feature.csv
safeu-0.1.0.dist-info/LICENSE
safeu-0.1.0.dist-info/METADATA
safeu-0.1.0.dist-info/WHEEL
safeu-0.1.0.dist-info/top_level.txt
safeu-0.1.0.dist-info/RECORD
