Metadata-Version: 2.1
Name: safeu
Version: 0.1.0
Summary: Safe learning for unlabeled data
Home-page: https://git.nju.edu.cn/lamda/safeu
Author: De-Ming Liang, Yu-Feng Li
Author-email: liangdm@lamda.nju.edu.cn, liyf@lamda.nju.edu.cn
License: UNKNOWN
Platform: UNKNOWN
Requires-Dist: numpy (>=1.15.1)
Requires-Dist: scipy (>=1.1.0)
Requires-Dist: scikit-learn (>=0.19.2)
Requires-Dist: cvxopt (>=1.2.0)
